useful_utilities/__init__.py
useful_utilities/pyrogram.py
useful_utilities/time_utilities.py
useful_utilities/utilities.py
useful_utilities-1.0.1.dist-info/WHEEL
useful_utilities-1.0.1.dist-info/METADATA
useful_utilities-1.0.1.dist-info/RECORD
