Metadata-Version: 2.1
Name: useful-utilities
Version: 1.0.1
Summary: Various useful utilities that I created when I didn't find an alternative.
Home-page: https://github.com/lzrdblzzrd/useful-utilities
Keywords: lzrdblzzrd,useful,utilities
Author: lzrdblzzrd
Author-email: lzrdblzzrd@gmail.com
Requires-Python: >=3.8,<4.0
Classifier: Programming Language :: Python :: 3
Classifier: Programming Language :: Python :: 3.10
Classifier: Programming Language :: Python :: 3.8
Classifier: Programming Language :: Python :: 3.9
Requires-Dist: requests (>=2.27.1,<3.0.0)
Project-URL: Repository, https://github.com/lzrdblzzrd/useful-utilities
